srec_nlp/__init__.py
srec_nlp/common.py
srec_nlp/exc.py
srec_nlp/srec_nlp.py
srec_nlp-0.3.3.dist-info/WHEEL
srec_nlp-0.3.3.dist-info/METADATA
srec_nlp-0.3.3.dist-info/RECORD
