Metadata-Version: 2.1
Name: srec-nlp
Version: 0.3.3
Summary: 
Author: Stelios Tymvios
Author-email: stelios.tymvios@icloud.com
Requires-Python: >=3.6,<4.0
Classifier: Programming Language :: Python :: 3
Classifier: Programming Language :: Python :: 3.6
Classifier: Programming Language :: Python :: 3.7
Requires-Dist: Cython (>=0.29.9,<0.30.0)
Requires-Dist: attrs (>=19.1,<20.0)
Requires-Dist: aylien-apiclient (>=0.7.0,<0.8.0)
Requires-Dist: google-cloud (>=0.34.0,<0.35.0)
Requires-Dist: google-cloud-language (>=1.2,<2.0)
Requires-Dist: ibm-watson (>=3.0,<4.0)
Requires-Dist: more_itertools (>=7.1,<8.0)
Requires-Dist: numpy (>=1.16,<2.0)
Requires-Dist: paralleldots (>=3.2,<4.0)
Requires-Dist: pybind11 (>=2.2,<3.0)
Requires-Dist: requests (>=2.22,<3.0)
Requires-Dist: sklearn (>=0.0.0,<0.0.1)
Requires-Dist: trio (>=0.11.0,<0.12.0)
